trainsegmentation/__init__.py
trainsegmentation/trainsegmentation.py
trainsegmentation-0.1.8.dist-info/METADATA
trainsegmentation-0.1.8.dist-info/WHEEL
trainsegmentation-0.1.8.dist-info/top_level.txt
trainsegmentation-0.1.8.dist-info/RECORD
